cli_games/__init__.py
cli_games/guess_the_number.py
cli_games/math_quiz_duel.py
cli_games/typing_speed_race.py
cli_games_hnd68-0.1.1.dist-info/licenses/LICENSE
cli_games_hnd68-0.1.1.dist-info/METADATA
cli_games_hnd68-0.1.1.dist-info/WHEEL
cli_games_hnd68-0.1.1.dist-info/entry_points.txt
cli_games_hnd68-0.1.1.dist-info/top_level.txt
cli_games_hnd68-0.1.1.dist-info/RECORD
