Metadata-Version: 2.4
Name: cli-games-hnd68
Version: 0.1.1
Summary: Fun CLI games: Number Guessing Duel, Math Quiz Duel, Typing Speed Race
Home-page: https://github.com/Orgpg/CLI-Game
Author: Wai Phyo Aung
Author-email: info@waiphyoaung.dev
Classifier: Programming Language :: Python :: 3
Classifier: License :: OSI Approved :: MIT License
Classifier: Operating System :: OS Independent
Requires-Python: >=3.7
License-File: LICENSE
Dynamic: author
Dynamic: author-email
Dynamic: classifier
Dynamic: home-page
Dynamic: license-file
Dynamic: requires-python
Dynamic: summary
